autoforge/__init__.py
autoforge/__main__.py
autoforge/auto_forge.py
autoforge/priority_mask_editor.py
autoforge/Helper/AmpUtils.py
autoforge/Helper/CAdamW.py
autoforge/Helper/FilamentHelper.py
autoforge/Helper/ImageHelper.py
autoforge/Helper/OptimizerHelper.py
autoforge/Helper/OtherHelper.py
autoforge/Helper/OutputHelper.py
autoforge/Helper/PruningHelper.py
autoforge/Helper/__init__.py
autoforge/Helper/filamentcolors_library.py
autoforge/Helper/Heightmaps/ChristofidesHeightMap.py
autoforge/Helper/Heightmaps/DepthEstimateHeightMap.py
autoforge/Helper/Heightmaps/__init__.py
autoforge/Init_comparer/__init__.py
autoforge/Init_comparer/auto_forge_init_check.py
autoforge/Init_comparer/plot_results.py
autoforge/Loss/LossFunctions.py
autoforge/Loss/PerceptionLoss.py
autoforge/Loss/__init__.py
autoforge/Misc/__init__.py
autoforge/Misc/color_fit_all.py
autoforge/Modules/Optimizer.py
autoforge/Modules/__init__.py
autoforge-1.9.3.1.dist-info/METADATA
autoforge-1.9.3.1.dist-info/WHEEL
autoforge-1.9.3.1.dist-info/entry_points.txt
autoforge-1.9.3.1.dist-info/top_level.txt
autoforge-1.9.3.1.dist-info/RECORD
