Metadata-Version: 2.4
Name: AutoForge
Version: 1.9.3.1
Summary: AutoForge is a Python tool for generating 3D printed layered models from an input image.
Author-email: Hendric Voss <hvoss@techfak.uni-bielefeld.de>
License: CC BY-NC-SA 4.0
Requires-Python: >=3.10
Requires-Dist: numpy
Requires-Dist: torch>=2.9.1
Requires-Dist: torchvision>=0.21.0
Requires-Dist: transformers>=4.48.1
Requires-Dist: opencv-python>=4.2.0.32
Requires-Dist: matplotlib>=3.3.0
Requires-Dist: configargparse>=1.2.3
Requires-Dist: tqdm>=4.50.0
Requires-Dist: pandas>=1.1.0
Requires-Dist: scikit-image
Requires-Dist: scikit-learn
Requires-Dist: tensorboard
Requires-Dist: pillow>=11.1.0
Requires-Dist: shapely>=2.0.7
Requires-Dist: trimesh>=4.6.4
Requires-Dist: joblib>=1.4.2
